HWVL/HWVL.py
HWVL/__init__.py
hwvl-0.0.1.dist-info/METADATA
hwvl-0.0.1.dist-info/WHEEL
hwvl-0.0.1.dist-info/top_level.txt
hwvl-0.0.1.dist-info/RECORD
