Metadata-Version: 2.4
Name: HWVL
Version: 0.0.1
Summary: The first Iranian hash
Home-page: https://github.com/HWVL/hash-HWVL
Author: mohammad rakhshkhorshid
Author-email: mohammad.rakhshkhorshid@gmail.com
Classifier: Programming Language :: Python :: 3
Classifier: Operating System :: OS Independent
Requires-Python: >=3.6
Dynamic: author
Dynamic: author-email
Dynamic: classifier
Dynamic: description
Dynamic: description-content-type
Dynamic: home-page
Dynamic: requires-python
Dynamic: summary
